organsync/__init__.py
organsync/version.py
organsync/data/__init__.py
organsync/data/data_module.py
organsync/experiments/__init__.py
organsync/experiments/data/__init__.py
organsync/experiments/data/data_module.py
organsync/experiments/data/utils.py
organsync/models/__init__.py
organsync/models/confidentmatch.py
organsync/models/inference.py
organsync/models/linear.py
organsync/models/multitask.py
organsync/models/organite_network.py
organsync/models/organsync_network.py
organsync/models/transplantbenefit.py
organsync/models/utils.py
organsync/models/third_party/__init__.py
organsync/models/third_party/tbs/__init__.py
organsync/models/third_party/tbs/betas.csv
organsync/models/third_party/tbs/surv_cancer.csv
organsync/models/third_party/tbs/surv_noncancer.csv
organsync/models/third_party/tbs/tbs.py
organsync/policies/__init__.py
organsync/policies/base.py
organsync/policies/policy.py
organsync/simulation/__init__.py
organsync/simulation/simulation.py
organsync/survival_analysis/__init__.py
organsync/survival_analysis/cox_ph.py
organsync/survival_analysis/xgboost.py
organsync-0.1.5.dist-info/METADATA
organsync-0.1.5.dist-info/WHEEL
organsync-0.1.5.dist-info/top_level.txt
organsync-0.1.5.dist-info/RECORD
