Metadata-Version: 2.1
Name: organsync
Version: 0.1.5
Summary: Learning Queueing Policies for Organ Transplantation Allocation using Interpretable Counterfactual Survival Analysis
Home-page: https://github.com/jeroenbe/organsync
Author: Jeroen Berrevoets
Author-email: jb2384@cam.ac.uk
License: BSD-3-Clause
Platform: UNKNOWN
Classifier: Programming Language :: Python :: 3
Classifier: Topic :: Scientific/Engineering :: Artificial Intelligence
Classifier: Intended Audience :: Healthcare Industry
Classifier: License :: OSI Approved :: BSD License
Classifier: Operating System :: OS Independent
Requires-Dist: cvxpy
Requires-Dist: joblib
Requires-Dist: lifelines (>=0.27)
Requires-Dist: numpy (>=1.21.0)
Requires-Dist: pandas (>=1.3.5)
Requires-Dist: pytorch-lightning (>=1.4.9)
Requires-Dist: scikit-learn (>=1.0.0)
Requires-Dist: torch (>=1.9.0)
Requires-Dist: xgbse
